LICENSE
MANIFEST.in
README.rst
setup.py
rlib_log.egg-info/PKG-INFO
rlib_log.egg-info/SOURCES.txt
rlib_log.egg-info/dependency_links.txt
rlib_log.egg-info/not-zip-safe
rlib_log.egg-info/top_level.txt
rlog/__init__.py