Metadata-Version: 1.1
Name: rlib-log
Version: 0.1
Summary: Tag-based logging for Python 3.
Home-page: https://github.com/t5w5h5/rlog
Author: t5w5h5
Author-email: t5w5h5@gmail.com
License: MIT
Download-URL: https://github.com/t5w5h5/rlog/archive/0.1.tar.gz
Keywords: logging
Platform: any
Classifier: Development Status :: 4 - Beta
Classifier: Intended Audience :: Developers
Classifier: License :: OSI Approved :: MIT License
Classifier: Natural Language :: English
Classifier: Operating System :: OS Independent
Classifier: Programming Language :: Python :: 3.6
Classifier: Programming Language :: Python
Classifier: Topic :: Software Development :: Libraries :: Python Modules
